sitemap/__init__.py
sitemap/baidu.py
sitemap/generator.py
sitemap/ping.py
sitemap/spider.py
sitemap_python-0.2.0.dist-info/DESCRIPTION.rst
sitemap_python-0.2.0.dist-info/METADATA
sitemap_python-0.2.0.dist-info/RECORD
sitemap_python-0.2.0.dist-info/WHEEL
sitemap_python-0.2.0.dist-info/metadata.json
sitemap_python-0.2.0.dist-info/top_level.txt
