Metadata-Version: 2.0
Name: sitemap-python
Version: 0.2.0
Summary: UNKNOWN
Home-page: https://github.com/socrateslee/sitemap_python
Author: Lichun
Author-email: UNKNOWN
License: MIT
Platform: UNKNOWN
Classifier: Environment :: Console
Classifier: Framework :: Django
Classifier: Intended Audience :: Developers
Classifier: License :: OSI Approved :: MIT License
Classifier: Programming Language :: Python
Requires-Dist: six
